CHANGES.rst
MANIFEST.in
README.rst
setup.cfg
setup.py
docs/LICENSE.GPL
docs/LICENSE.txt
docs/request.txt
plone4/__init__.py
plone4.csrffixes.egg-info/PKG-INFO
plone4.csrffixes.egg-info/SOURCES.txt
plone4.csrffixes.egg-info/dependency_links.txt
plone4.csrffixes.egg-info/entry_points.txt
plone4.csrffixes.egg-info/namespace_packages.txt
plone4.csrffixes.egg-info/not-zip-safe
plone4.csrffixes.egg-info/requires.txt
plone4.csrffixes.egg-info/top_level.txt
plone4/csrffixes/__init__.py
plone4/csrffixes/configure.zcml
plone4/csrffixes/patches.py
plone4/csrffixes/protect.js
plone4/csrffixes/transform.py