Metadata-Version: 2.1
Name: plone4.csrffixes
Version: 1.1.1
Summary: CSRF fixes for Plone 4
Home-page: http://pypi.python.org/pypi/plone4.csrffixes
Author: Plone Foundation
Author-email: plone-developers@lists.sourceforge.net
License: GPL version 2
Keywords: plone csrf
Platform: UNKNOWN
Classifier: Framework :: Plone
Classifier: Programming Language :: Python
Classifier: Programming Language :: Python :: 2.6
Classifier: Programming Language :: Python :: 2.7
Provides-Extra: test
